xbrlapi/__init__.py
xbrlapi/api.py
xbrlapi-0.1.5.dist-info/METADATA
xbrlapi-0.1.5.dist-info/WHEEL
xbrlapi-0.1.5.dist-info/top_level.txt
xbrlapi-0.1.5.dist-info/RECORD
