Metadata-Version: 2.1
Name: xbrlapi
Version: 0.1.5
Summary: A Python client for XBRLAPI
Home-page: https://github.com/TomasMiloCA/xbrlapi
Author: Tomas Milo
Author-email: tomas.sam.milo@gmail.com
License: UNKNOWN
Platform: UNKNOWN
Classifier: Programming Language :: Python :: 3
Classifier: License :: OSI Approved :: MIT License
Classifier: Operating System :: OS Independent
Requires-Python: >=3.6
Requires-Dist: pandas
Requires-Dist: python-dotenv
Requires-Dist: requests
Requires-Dist: supabase
